sphinx_markdown_tables/__init__.py
sphinx_markdown_tables/__version__.py
sphinx_markdown_tables-0.0.17.data/data/LICENSE
sphinx_markdown_tables-0.0.17.dist-info/LICENSE
sphinx_markdown_tables-0.0.17.dist-info/METADATA
sphinx_markdown_tables-0.0.17.dist-info/WHEEL
sphinx_markdown_tables-0.0.17.dist-info/top_level.txt
sphinx_markdown_tables-0.0.17.dist-info/RECORD
