Metadata-Version: 2.1
Name: sphinx-markdown-tables
Version: 0.0.17
Summary: A Sphinx extension for rendering tables written in markdown
Home-page: https://github.com/ryanfox/sphinx-markdown-tables
Author: Ryan Fox
Author-email: ryan@foxrow.com
Project-URL: Bug Reports, https://github.com/ryanfox/sphinx-markdown-tables/issues
Project-URL: Say Thanks!, https://foxrow.com
Project-URL: Source, https://github.com/ryanfox/sphinx-markdown-tables/
Keywords: sphinx markdown tables
Classifier: Development Status :: 4 - Beta
Classifier: Intended Audience :: Developers
Classifier: Topic :: Software Development :: Build Tools
Classifier: License :: OSI Approved :: GNU General Public License v3 (GPLv3)
Classifier: Programming Language :: Python :: 3.5
Classifier: Programming Language :: Python :: 3.6
License-File: LICENSE
